LICENSE
pycheckpoint_api/__init__.py
pycheckpoint_api/management/__init__.py
pycheckpoint_api/management/abstract/network_object.py
pycheckpoint_api/management/access_control_nat/__init__.py
pycheckpoint_api/management/access_control_nat/access_layer.py
pycheckpoint_api/management/access_control_nat/access_rule.py
pycheckpoint_api/management/access_control_nat/access_section.py
pycheckpoint_api/management/access_control_nat/nat_rule.py
pycheckpoint_api/management/access_control_nat/nat_section.py
pycheckpoint_api/management/exception.py
pycheckpoint_api/management/misc/__init__.py
pycheckpoint_api/management/misc/generic_objects.py
pycheckpoint_api/management/network_objects/__init__.py
pycheckpoint_api/management/network_objects/access_point_name.py
pycheckpoint_api/management/network_objects/address_range.py
pycheckpoint_api/management/network_objects/checkpoint_host.py
pycheckpoint_api/management/network_objects/dns_domain.py
pycheckpoint_api/management/network_objects/dynamic_object.py
pycheckpoint_api/management/network_objects/group.py
pycheckpoint_api/management/network_objects/group_with_exclusion.py
pycheckpoint_api/management/network_objects/gsn_handover_group.py
pycheckpoint_api/management/network_objects/host.py
pycheckpoint_api/management/network_objects/lsm_cluster.py
pycheckpoint_api/management/network_objects/lsm_gateway.py
pycheckpoint_api/management/network_objects/lsv_profile.py
pycheckpoint_api/management/network_objects/multicast_address_range.py
pycheckpoint_api/management/network_objects/network.py
pycheckpoint_api/management/network_objects/network_interface.py
pycheckpoint_api/management/network_objects/opsec_application.py
pycheckpoint_api/management/network_objects/security_zone.py
pycheckpoint_api/management/network_objects/simple_cluster.py
pycheckpoint_api/management/network_objects/simple_gateway.py
pycheckpoint_api/management/network_objects/tacacs_group.py
pycheckpoint_api/management/network_objects/tacacs_server.py
pycheckpoint_api-1.1.4.dist-info/LICENSE
pycheckpoint_api-1.1.4.dist-info/WHEEL
pycheckpoint_api-1.1.4.dist-info/METADATA
pycheckpoint_api-1.1.4.dist-info/RECORD
