Metadata-Version: 2.1
Name: pycheckpoint-api
Version: 1.1.4
Summary: A python SDK for the Checkpoint firewalls
Home-page: https://github.com/LetMeR00t/pyCheckpoint-API
License: MIT
Author: LmR
Author-email: letmer00t@gmail.com
Requires-Python: >=3.7,<4.0
Classifier: Environment :: Console
Classifier: Intended Audience :: Developers
Classifier: Intended Audience :: Information Technology
Classifier: Intended Audience :: System Administrators
Classifier: License :: OSI Approved :: MIT License
Classifier: Natural Language :: English
Classifier: Programming Language :: Python :: 3
Classifier: Programming Language :: Python :: 3.10
Classifier: Programming Language :: Python :: 3.7
Classifier: Programming Language :: Python :: 3.8
Classifier: Programming Language :: Python :: 3.9
Classifier: Topic :: Security
Classifier: Topic :: Software Development :: Libraries :: Python Modules
Requires-Dist: restfly (>=1.4.6,<2.0.0)
Project-URL: Bug Tracker, https://github.com/LetMeR00t/pyCheckpoint-API/issues
Project-URL: Repository, https://github.com/LetMeR00t/pyCheckpoint-API
